{"org":"twitter","repository":[{"name":"dodo","data":{"commits":[{"sha":"60ca72e6eb644a42b513ee8fbf7600801ebab1e6","commit":{"author":{"name":"Bryce Anderson","email":"banderson@twitter.com","date":"2017-11-07T15:59:32Z"},"committer":{"name":"jenkins","email":"jenkins@smf1-eev-25-sr1.prod.twitter.com","date":"2017-11-07T16:46:13Z"},"title":"Update sbt to 1.0.3 and scala 2.12 to 2.12.4"},"html_url":"https://github.com/twitter/dodo/commit/60ca72e6eb644a42b513ee8fbf7600801ebab1e6","author":{"login":"bryce-anderson","html_url":"https://github.com/bryce-anderson"}},{"sha":"1f4239c47640b6b1e24f1e5caf5b4611a489ca62","commit":{"author":{"name":"Christopher Coco","email":"ccoco@twitter.com","date":"2017-11-01T20:35:07Z"},"committer":{"name":"jenkins","email":"jenkins@atla-bfy-34-sr3.prod.twttr.net","date":"2017-11-01T21:29:16Z"},"title":"dodo - Allow for easy deletion of caches and sbt-launch.jars"},"html_url":"https://github.com/twitter/dodo/commit/1f4239c47640b6b1e24f1e5caf5b4611a489ca62","author":{"login":"cacoco","html_url":"https://github.com/cacoco"}},{"sha":"76efab4c2bf531db1665c856e9b7ef50ed17bd1b","commit":{"author":{"name":"Moses Nakamura","email":"mnakamura@twitter.com","date":"2017-11-01T17:47:49Z"},"committer":{"name":"jenkins","email":"jenkins@smf1-fbk-37-sr1.prod.twitter.com","date":"2017-11-01T18:31:48Z"},"title":"csl: Migrate to sbt 1.0.0"},"html_url":"https://github.com/twitter/dodo/commit/76efab4c2bf531db1665c856e9b7ef50ed17bd1b","author":{"login":"mosesn","html_url":"https://github.com/mosesn"}},{"sha":"65a383bb6f5e5be1eba7e226c0a0340b63adf1b5","commit":{"author":{"name":"Stefan Lance","email":"slance@twitter.com","date":"2017-11-01T00:45:10Z"},"committer":{"name":"jenkins","email":"jenkins@smf1-bwi-37-sr4.prod.twitter.com","date":"2017-11-01T01:24:12Z"},"title":"util: Open-source IntelliJ async stack trace capture points"},"html_url":"https://github.com/twitter/dodo/commit/65a383bb6f5e5be1eba7e226c0a0340b63adf1b5","author":{"login":"smlance","html_url":"https://github.com/smlance"}},{"sha":"7b5c4107861062a4355415becfc5884b9578bf59","commit":{"author":{"name":"Daniel Schobel","email":"dschobel@twitter.com","date":"2017-08-16T23:52:17Z"},"committer":{"name":"jenkins","email":"jenkins@smf1-egq-12-sr1.prod.twitter.com","date":"2017-08-17T00:08:39Z"},"title":"dodo: disable sbt 1.0 for cross publishing"},"html_url":"https://github.com/twitter/dodo/commit/7b5c4107861062a4355415becfc5884b9578bf59","author":{"login":"dschobel","html_url":"https://github.com/dschobel"}},{"sha":"4df8a6a8b98ecb39e92c4be0fe08011a7e99d30b","commit":{"author":{"name":"Moses Nakamura","email":"mnakamura@twitter.com","date":"2017-08-11T23:03:24Z"},"committer":{"name":"jenkins","email":"jenkins@smf1-avl-25-sr4.prod.twitter.com","date":"2017-08-11T23:31:26Z"},"title":"dodo: Bump to sbt 1.0 for cross publishing"},"html_url":"https://github.com/twitter/dodo/commit/4df8a6a8b98ecb39e92c4be0fe08011a7e99d30b","author":{"login":"mosesn","html_url":"https://github.com/mosesn"}},{"sha":"f681cc19f370181a1998ad1ce3cc28ff7ea80972","commit":{"author":{"name":"Moses Nakamura","email":"mnakamura@twitter.com","date":"2017-08-08T22:39:40Z"},"committer":{"name":"jenkins","email":"jenkins@atla-atm-08-sr4.prod.twttr.net","date":"2017-08-09T02:11:34Z"},"title":"{dodo,scrooge}: cross publish scrooge-sbt-plugin to sbt 1.0"},"html_url":"https://github.com/twitter/dodo/commit/f681cc19f370181a1998ad1ce3cc28ff7ea80972","author":{"login":"mosesn","html_url":"https://github.com/mosesn"}},{"sha":"aefcc656c1093c088737291d6f13c37b76af7de1","commit":{"author":{"name":"Jillian Crossley","email":"jillianc@twitter.com","date":"2017-08-02T00:11:28Z"},"committer":{"name":"jenkins","email":"jenkins@atla-asb-14-sr4.prod.twttr.net","date":"2017-08-04T19:25:34Z"},"title":"dodo: Fix README example command to run dodo from parent dir."},"html_url":"https://github.com/twitter/dodo/commit/aefcc656c1093c088737291d6f13c37b76af7de1","author":{"login":"jcrossley","html_url":"https://github.com/jcrossley"}},{"sha":"369d28cf6d69c5be65c04cce7b996a7d5bd663d2","commit":{"author":{"name":"Kevin Oliver","email":"koliver@twitter.com","date":"2017-04-26T16:24:52Z"},"committer":{"name":"jenkins","email":"jenkins@atla-asa-22-sr1.prod.twttr.net","date":"2017-04-26T17:05:08Z"},"title":"Remove ostrich as a dependency"},"html_url":"https://github.com/twitter/dodo/commit/369d28cf6d69c5be65c04cce7b996a7d5bd663d2","author":{"login":"kevinoliver","html_url":"https://github.com/kevinoliver"}},{"sha":"d148ac26c0216cb035b47ac11eb7efb62662f725","commit":{"author":{"name":"Christopher Coco","email":"ccoco@twitter.com","date":"2017-02-17T21:16:53Z"},"committer":{"name":"jenkins","email":"jenkins@atla-asa-22-sr1.prod.twttr.net","date":"2017-02-17T22:01:14Z"},"title":"dodo: Update to support local m2 publishing"},"html_url":"https://github.com/twitter/dodo/commit/d148ac26c0216cb035b47ac11eb7efb62662f725","author":{"login":"cacoco","html_url":"https://github.com/cacoco"}},{"sha":"7df6dc2a9b965e7a3cf27108b5d59fcf12ef20c7","commit":{"author":{"name":"Christopher Coco","email":"ccoco@twitter.com","date":"2016-08-26T22:10:48Z"},"committer":{"name":"jenkins","email":"jenkins@atla-agh-08-sr4.prod.twttr.net","date":"2016-08-29T20:02:10Z"},"title":"dodo: Add ability to clean, set remote branch and fix md5 hashing"},"html_url":"https://github.com/twitter/dodo/commit/7df6dc2a9b965e7a3cf27108b5d59fcf12ef20c7","author":{"login":"cacoco","html_url":"https://github.com/cacoco"}},{"sha":"0cf9106d16df4a5b04f7b4879c431d315422ef3a","commit":{"author":{"name":"Christopher Coco","email":"ccoco@twitter.com","date":"2016-08-11T00:13:03Z"},"committer":{"name":"jenkins","email":"jenkins@atla-agh-08-sr4.prod.twttr.net","date":"2016-08-11T00:20:53Z"},"title":"dodo: Add retry to commands"},"html_url":"https://github.com/twitter/dodo/commit/0cf9106d16df4a5b04f7b4879c431d315422ef3a","author":{"login":"cacoco","html_url":"https://github.com/cacoco"}},{"sha":"d593853762059e102328839748a946ea0f4f86ba","commit":{"author":{"name":"Christopher Coco","email":"ccoco@twitter.com","date":"2016-07-22T20:29:15Z"},"committer":{"name":"jenkins","email":"jenkins@atla-agh-08-sr4.prod.twttr.net","date":"2016-07-22T20:32:18Z"},"title":"Dodo: Don't use bash bc"},"html_url":"https://github.com/twitter/dodo/commit/d593853762059e102328839748a946ea0f4f86ba","author":{"login":"cacoco","html_url":"https://github.com/cacoco"}},{"sha":"1ba34a4d37b923d76a4910eb30c4c3f97d2541a8","commit":{"author":{"name":"Christopher Coco","email":"ccoco@twitter.com","date":"2016-07-22T19:00:24Z"},"committer":{"name":"jenkins","email":"jenkins@atla-agh-08-sr4.prod.twttr.net","date":"2016-07-22T19:06:30Z"},"title":"Dodo: Update TravisCI to do a dry-run"},"html_url":"https://github.com/twitter/dodo/commit/1ba34a4d37b923d76a4910eb30c4c3f97d2541a8","author":{"login":"cacoco","html_url":"https://github.com/cacoco"}},{"sha":"4ec456f0216dd41c42c76403676c5b85535c6a9d","commit":{"author":{"name":"Christopher Coco","email":"ccoco@twitter.com","date":"2016-07-22T17:09:50Z"},"committer":{"name":"jenkins","email":"jenkins@atla-atd-29-sr1.prod.twttr.net","date":"2016-07-22T17:11:50Z"},"title":"dodo: Add project badges to README.md"},"html_url":"https://github.com/twitter/dodo/commit/4ec456f0216dd41c42c76403676c5b85535c6a9d","author":{"login":"cacoco","html_url":"https://github.com/cacoco"}},{"sha":"4f1b379cd57173d8360f60ceccf002eaefefad47","commit":{"author":{"name":"Christopher Coco","email":"ccoco@twitter.com","date":"2016-07-21T20:51:10Z"},"committer":{"name":"Christopher Coco","email":"ccoco@twitter.com","date":"2016-07-21T20:51:10Z"},"title":"Removed"},"html_url":"https://github.com/twitter/dodo/commit/4f1b379cd57173d8360f60ceccf002eaefefad47","author":{"login":"cacoco","html_url":"https://github.com/cacoco"},"committer":{"login":"cacoco","html_url":"https://github.com/cacoco"}},{"sha":"8f296f6eebed4cfb24586083a2bdc46c23c79caf","commit":{"author":{"name":"Christopher Coco","email":"ccoco@twitter.com","date":"2016-07-21T20:50:01Z"},"committer":{"name":"Christopher Coco","email":"ccoco@twitter.com","date":"2016-07-21T20:50:01Z"},"title":"Removed"},"html_url":"https://github.com/twitter/dodo/commit/8f296f6eebed4cfb24586083a2bdc46c23c79caf","author":{"login":"cacoco","html_url":"https://github.com/cacoco"},"committer":{"login":"cacoco","html_url":"https://github.com/cacoco"}},{"sha":"9c26d8341fe41d15d9acd35cc1c334d45c8ec99a","commit":{"author":{"name":"Christopher Coco","email":"ccoco@twitter.com","date":"2016-07-21T19:17:37Z"},"committer":{"name":"Christopher Coco","email":"ccoco@twitter.com","date":"2016-07-21T20:45:20Z"},"title":"[Dodo]: Update hash command and fix issue around caching previous builds."},"html_url":"https://github.com/twitter/dodo/commit/9c26d8341fe41d15d9acd35cc1c334d45c8ec99a","author":{"login":"cacoco","html_url":"https://github.com/cacoco"},"committer":{"login":"cacoco","html_url":"https://github.com/cacoco"}},{"sha":"a033abc3a751badd2d8f878b24ab3de939fc0b16","commit":{"author":{"name":"Christopher Coco","email":"ccoco@twitter.com","date":"2016-07-21T17:58:01Z"},"committer":{"name":"Christopher Coco","email":"ccoco@twitter.com","date":"2016-07-21T20:45:20Z"},"title":"Dodo -- the Twitter OSS project builder"},"html_url":"https://github.com/twitter/dodo/commit/a033abc3a751badd2d8f878b24ab3de939fc0b16","author":{"login":"cacoco","html_url":"https://github.com/cacoco"},"committer":{"login":"cacoco","html_url":"https://github.com/cacoco"}},{"sha":"16f116e2c044a405e23591e7d5f6941021a8110d","commit":{"author":{"name":"Christopher Coco","email":"ccoco@twitter.com","date":"2016-07-21T17:14:22Z"},"committer":{"name":"Christopher Coco","email":"ccoco@twitter.com","date":"2016-07-21T17:14:22Z"},"title":"Initial commit"},"html_url":"https://github.com/twitter/dodo/commit/16f116e2c044a405e23591e7d5f6941021a8110d","author":{"login":"cacoco","html_url":"https://github.com/cacoco"},"committer":{"login":"cacoco","html_url":"https://github.com/cacoco"}}],"issues":[],"pulls":[]}}]}